{
  "levels": [
    {
      "Level": 0,
      "Ruleset": {
        "RandomizerName": null,
        "RotatorName": null,
        "visibleNextCount": 1,
        "ghostEnabled": true,
        "initialLevel": 0,
        "gravity": 30,
        "holdEnabled": true,
        "appearanceDelay": 27,
        "lineclearDelay": 40,
        "dasTime": 16,
        "lockInDelay": 30,
        "InstalockOnHardDrop": false
      }
    },
    {
      "Level": 30,
      "Ruleset": {
        "RandomizerName": null,
        "RotatorName": null,
        "visibleNextCount": 1,
        "ghostEnabled": true,
        "initialLevel": 0,
        "gravity": 24,
        "holdEnabled": true,
        "appearanceDelay": 27,
        "lineclearDelay": 40,
        "dasTime": 16,
        "lockInDelay": 30,
        "InstalockOnHardDrop": false
      }
    },
    {
      "Level": 35,
      "Ruleset": {
        "RandomizerName": null,
        "RotatorName": null,
        "visibleNextCount": 1,
        "ghostEnabled": true,
        "initialLevel": 0,
        "gravity": 22,
        "holdEnabled": true,
        "appearanceDelay": 27,
        "lineclearDelay": 40,
        "dasTime": 16,
        "lockInDelay": 30,
        "InstalockOnHardDrop": false
      }
    },
    {
      "Level": 40,
      "Ruleset": {
        "RandomizerName": null,
        "RotatorName": null,
        "visibleNextCount": 1,
        "ghostEnabled": true,
        "initialLevel": 0,
        "gravity": 18,
        "holdEnabled": true,
        "appearanceDelay": 27,
        "lineclearDelay": 40,
        "dasTime": 16,
        "lockInDelay": 30,
        "InstalockOnHardDrop": false
      }
    },
    {
      "Level": 50,
      "Ruleset": {
        "RandomizerName": null,
        "RotatorName": null,
        "visibleNextCount": 1,
        "ghostEnabled": true,
        "initialLevel": 0,
        "gravity": 14,
        "holdEnabled": true,
        "appearanceDelay": 27,
        "lineclearDelay": 40,
        "dasTime": 16,
        "lockInDelay": 30,
        "InstalockOnHardDrop": false
      }
    },
    {
      "Level": 60,
      "Ruleset": {
        "RandomizerName": null,
        "RotatorName": null,
        "visibleNextCount": 1,
        "ghostEnabled": true,
        "initialLevel": 0,
        "gravity": 12,
        "holdEnabled": true,
        "appearanceDelay": 27,
        "lineclearDelay": 40,
        "dasTime": 16,
        "lockInDelay": 30,
        "InstalockOnHardDrop": false
      }
    },
    {
      "Level": 70,
      "Ruleset": {
        "RandomizerName": null,
        "RotatorName": null,
        "visibleNextCount": 1,
        "ghostEnabled": true,
        "initialLevel": 0,
        "gravity": 8,
        "holdEnabled": true,
        "appearanceDelay": 27,
        "lineclearDelay": 40,
        "dasTime": 16,
        "lockInDelay": 30,
        "InstalockOnHardDrop": false
      }
    },
    {
      "Level": 80,
      "Ruleset": {
        "RandomizerName": null,
        "RotatorName": null,
        "visibleNextCount": 1,
        "ghostEnabled": true,
        "initialLevel": 0,
        "gravity": 6,
        "holdEnabled": true,
        "appearanceDelay": 27,
        "lineclearDelay": 40,
        "dasTime": 16,
        "lockInDelay": 30,
        "InstalockOnHardDrop": false
      }
    },
    {
      "Level": 90,
      "Ruleset": {
        "RandomizerName": null,
        "RotatorName": null,
        "visibleNextCount": 1,
        "ghostEnabled": true,
        "initialLevel": 0,
        "gravity": 4,
        "holdEnabled": true,
        "appearanceDelay": 27,
        "lineclearDelay": 40,
        "dasTime": 16,
        "lockInDelay": 30,
        "InstalockOnHardDrop": false
      }
    },
    {
      "Level": 100,
      "Ruleset": {
        "RandomizerName": null,
        "RotatorName": null,
        "visibleNextCount": 1,
        "ghostEnabled": true,
        "initialLevel": 0,
        "gravity": 3,
        "holdEnabled": true,
        "appearanceDelay": 27,
        "lineclearDelay": 40,
        "dasTime": 16,
        "lockInDelay": 30,
        "InstalockOnHardDrop": false
      }
    },
    {
      "Level": 120,
      "Ruleset": {
        "RandomizerName": null,
        "RotatorName": null,
        "visibleNextCount": 1,
        "ghostEnabled": true,
        "initialLevel": 0,
        "gravity": 2,
        "holdEnabled": true,
        "appearanceDelay": 27,
        "lineclearDelay": 40,
        "dasTime": 16,
        "lockInDelay": 30,
        "InstalockOnHardDrop": false
      }
    },
    {
      "Level": 140,
      "Ruleset": {
        "RandomizerName": null,
        "RotatorName": null,
        "visibleNextCount": 1,
        "ghostEnabled": true,
        "initialLevel": 0,
        "gravity": 1,
        "holdEnabled": true,
        "appearanceDelay": 27,
        "lineclearDelay": 40,
        "dasTime": 5,
        "lockInDelay": 30,
        "InstalockOnHardDrop": false
      }
    },
    {
      "Level": 170,
      "Ruleset": {
        "RandomizerName": null,
        "RotatorName": null,
        "visibleNextCount": 1,
        "ghostEnabled": true,
        "initialLevel": 0,
        "gravity": 0,
        "holdEnabled": true,
        "appearanceDelay": 27,
        "lineclearDelay": 40,
        "dasTime": 16,
        "lockInDelay": 30,
        "InstalockOnHardDrop": false
      }
    },
    {
      "Level": 200,
      "Ruleset": {
        "RandomizerName": null,
        "RotatorName": null,
        "visibleNextCount": 1,
        "ghostEnabled": true,
        "initialLevel": 0,
        "gravity": 30,
        "holdEnabled": true,
        "appearanceDelay": 27,
        "lineclearDelay": 40,
        "dasTime": 16,
        "lockInDelay": 30,
        "InstalockOnHardDrop": false
      }
    },
    {
      "Level": 220,
      "Ruleset": {
        "RandomizerName": null,
        "RotatorName": null,
        "visibleNextCount": 1,
        "ghostEnabled": true,
        "initialLevel": 0,
        "gravity": 8,
        "holdEnabled": true,
        "appearanceDelay": 27,
        "lineclearDelay": 40,
        "dasTime": 16,
        "lockInDelay": 30,
        "InstalockOnHardDrop": false
      }
    },
    {
      "Level": 230,
      "Ruleset": {
        "RandomizerName": null,
        "RotatorName": null,
        "visibleNextCount": 1,
        "ghostEnabled": true,
        "initialLevel": 0,
        "gravity": 6,
        "holdEnabled": true,
        "appearanceDelay": 27,
        "lineclearDelay": 40,
        "dasTime": 16,
        "lockInDelay": 30,
        "InstalockOnHardDrop": false
      }
    },
    {
      "Level": 233,
      "Ruleset": {
        "RandomizerName": null,
        "RotatorName": null,
        "visibleNextCount": 1,
        "ghostEnabled": true,
        "initialLevel": 0,
        "gravity": 4,
        "holdEnabled": true,
        "appearanceDelay": 27,
        "lineclearDelay": 40,
        "dasTime": 16,
        "lockInDelay": 30,
        "InstalockOnHardDrop": false
      }
    },
    {
      "Level": 239,
      "Ruleset": {
        "RandomizerName": null,
        "RotatorName": null,
        "visibleNextCount": 1,
        "ghostEnabled": true,
        "initialLevel": 0,
        "gravity": 2,
        "holdEnabled": true,
        "appearanceDelay": 27,
        "lineclearDelay": 40,
        "dasTime": 16,
        "lockInDelay": 30,
        "InstalockOnHardDrop": false
      }
    },
    {
      "Level": 243,
      "Ruleset": {
        "RandomizerName": null,
        "RotatorName": null,
        "visibleNextCount": 1,
        "ghostEnabled": true,
        "initialLevel": 0,
        "gravity": 1,
        "holdEnabled": true,
        "appearanceDelay": 27,
        "lineclearDelay": 40,
        "dasTime": 16,
        "lockInDelay": 30,
        "InstalockOnHardDrop": false
      }
    },
    {
      "Level": 247,
      "Ruleset": {
        "RandomizerName": null,
        "RotatorName": null,
        "visibleNextCount": 1,
        "ghostEnabled": true,
        "initialLevel": 0,
        "gravity": 0,
        "holdEnabled": true,
        "appearanceDelay": 27,
        "lineclearDelay": 40,
        "dasTime": 16,
        "lockInDelay": 30,
        "InstalockOnHardDrop": false
      }
    },
    {
      "Level": 251,
      "Ruleset": {
        "RandomizerName": null,
        "RotatorName": null,
        "visibleNextCount": 1,
        "ghostEnabled": true,
        "initialLevel": 0,
        "gravity": -1,
        "holdEnabled": true,
        "appearanceDelay": 27,
        "lineclearDelay": 40,
        "dasTime": 16,
        "lockInDelay": 30,
        "InstalockOnHardDrop": false
      }
    },
    {
      "Level": 300,
      "Ruleset": {
        "RandomizerName": null,
        "RotatorName": null,
        "visibleNextCount": 1,
        "ghostEnabled": true,
        "initialLevel": 0,
        "gravity": -2,
        "holdEnabled": true,
        "appearanceDelay": 27,
        "lineclearDelay": 40,
        "dasTime": 16,
        "lockInDelay": 30,
        "InstalockOnHardDrop": false
      }
    },
    {
      "Level": 330,
      "Ruleset": {
        "RandomizerName": null,
        "RotatorName": null,
        "visibleNextCount": 1,
        "ghostEnabled": true,
        "initialLevel": 0,
        "gravity": -3,
        "holdEnabled": true,
        "appearanceDelay": 27,
        "lineclearDelay": 40,
        "dasTime": 16,
        "lockInDelay": 30,
        "InstalockOnHardDrop": false
      }
    },
    {
      "Level": 360,
      "Ruleset": {
        "RandomizerName": null,
        "RotatorName": null,
        "visibleNextCount": 1,
        "ghostEnabled": true,
        "initialLevel": 0,
        "gravity": -4,
        "holdEnabled": true,
        "appearanceDelay": 27,
        "lineclearDelay": 40,
        "dasTime": 16,
        "lockInDelay": 30,
        "InstalockOnHardDrop": false
      }
    },
    {
      "Level": 400,
      "Ruleset": {
        "RandomizerName": null,
        "RotatorName": null,
        "visibleNextCount": 1,
        "ghostEnabled": true,
        "initialLevel": 0,
        "gravity": -5,
        "holdEnabled": true,
        "appearanceDelay": 27,
        "lineclearDelay": 40,
        "dasTime": 16,
        "lockInDelay": 30,
        "InstalockOnHardDrop": false
      }
    },
    {
      "Level": 420,
      "Ruleset": {
        "RandomizerName": null,
        "RotatorName": null,
        "visibleNextCount": 1,
        "ghostEnabled": true,
        "initialLevel": 0,
        "gravity": -4,
        "holdEnabled": true,
        "appearanceDelay": 27,
        "lineclearDelay": 40,
        "dasTime": 16,
        "lockInDelay": 30,
        "InstalockOnHardDrop": false
      }
    },
    {
      "Level": 450,
      "Ruleset": {
        "RandomizerName": null,
        "RotatorName": null,
        "visibleNextCount": 1,
        "ghostEnabled": true,
        "initialLevel": 0,
        "gravity": -3,
        "holdEnabled": true,
        "appearanceDelay": 27,
        "lineclearDelay": 40,
        "dasTime": 16,
        "lockInDelay": 30,
        "InstalockOnHardDrop": false
      }
    },
    {
      "Level": 500,
      "Ruleset": {
        "RandomizerName": null,
        "RotatorName": null,
        "visibleNextCount": 1,
        "ghostEnabled": true,
        "initialLevel": 0,
        "gravity":-20,
        "holdEnabled": true,
        "appearanceDelay": 27,
        "lineclearDelay": 25,
        "dasTime": 10,
        "lockInDelay": 30,
        "InstalockOnHardDrop": false
      }
    },
    {
      "Level": 600,
      "Ruleset": {
        "RandomizerName": null,
        "RotatorName": null,
        "visibleNextCount": 1,
        "ghostEnabled": true,
        "initialLevel": 0,
        "gravity":-20,
        "holdEnabled": true,
        "appearanceDelay": 27,
        "lineclearDelay": 16,
        "dasTime": 10,
        "lockInDelay": 30,
        "InstalockOnHardDrop": false
      }
    },
    {
      "Level": 700,
      "Ruleset": {
        "RandomizerName": null,
        "RotatorName": null,
        "visibleNextCount": 1,
        "ghostEnabled": true,
        "initialLevel": 0,
        "gravity":-20,
        "holdEnabled": true,
        "appearanceDelay": 18,
        "lineclearDelay": 12,
        "dasTime": 10,
        "lockInDelay": 30,
        "InstalockOnHardDrop": false
      }
    },
    {
      "Level": 800,
      "Ruleset": {
        "RandomizerName": null,
        "RotatorName": null,
        "visibleNextCount": 1,
        "ghostEnabled": true,
        "initialLevel": 0,
        "gravity":-20,
        "holdEnabled": true,
        "appearanceDelay": 14,
        "lineclearDelay": 6,
        "dasTime": 10,
        "lockInDelay": 30,
        "InstalockOnHardDrop": false
      }
    },
    {
      "Level": 900,
      "Ruleset": {
        "RandomizerName": null,
        "RotatorName": null,
        "visibleNextCount": 1,
        "ghostEnabled": true,
        "initialLevel": 0,
        "gravity":-20,
        "holdEnabled": true,
        "appearanceDelay": 14,
        "lineclearDelay": 6,
        "dasTime": 8,
        "lockInDelay": 17,
        "InstalockOnHardDrop": false
      }
    }
  ],
  "Name": "MTGM2",
  "Description": "The Second Master"
}